fast_rtsp/__init__.py
fast_rtsp/fast_rtsp.py
fast_rtsp/main.py
fast_rtsp-0.0.2.dist-info/LICENSE
fast_rtsp-0.0.2.dist-info/METADATA
fast_rtsp-0.0.2.dist-info/WHEEL
fast_rtsp-0.0.2.dist-info/top_level.txt
fast_rtsp-0.0.2.dist-info/RECORD
